rcode/__init__.py
rcode/__main__.py
rcode/rcode.py
rcode/rssh.py
rcode/ipc/__init__.py
rcode/ipc/ipc.py
rcode/ipc/ipc_runner.py
rcode-0.7.0.dist-info/LICENSE
rcode-0.7.0.dist-info/METADATA
rcode-0.7.0.dist-info/WHEEL
rcode-0.7.0.dist-info/entry_points.txt
rcode-0.7.0.dist-info/top_level.txt
rcode-0.7.0.dist-info/zip-safe
rcode-0.7.0.dist-info/RECORD
